yhy/__init__.py
yhy/__main__.py
yhy/commands/__init__.py
yhy/commands/bike.py
yhy/commands/boj.py
yhy/commands/clip.py
yhy/commands/anki/__init__.py
yhy/commands/anki/tts.py
yhy/commands/anki/word.py
yhy/commands/img/__init__.py
yhy/commands/img/half.py
yhy/commands/img/ocr.py
yhy/commands/img/paste.py
yhy/commands/img/sample.py
yhy/core/__init__.py
yhy/core/img/__init__.py
yhy/require/__init__.py
yhy-0.0.23.dist-info/LICENSE
yhy-0.0.23.dist-info/METADATA
yhy-0.0.23.dist-info/WHEEL
yhy-0.0.23.dist-info/entry_points.txt
yhy-0.0.23.dist-info/top_level.txt
yhy-0.0.23.dist-info/RECORD
