Metadata-Version: 2.1
Name: yhy
Version: 0.0.23
Summary: Personalized CLI
Home-page: https://github.com/yeonghoey/yhy
Author: Yeongho Kim
Author-email: yeonghoey@gmail.com
License: UNKNOWN
Keywords: automation cli anki
Platform: UNKNOWN
Classifier: License :: OSI Approved :: GNU General Public License v3 (GPLv3)
Classifier: Programming Language :: Python :: 3.6
Requires-Dist: Click
Requires-Dist: google-cloud-texttospeech
Requires-Dist: google-cloud-vision
Requires-Dist: lxml
Requires-Dist: pillow
Requires-Dist: prompt-toolkit
Requires-Dist: pyperclip
Requires-Dist: requests
